{
  "db_name": "SQLite",
  "query": "WITH RECURSIVE ancestors(id, depth) AS (\n                 SELECT parent_id, 0 FROM blocks WHERE id = ?\n                 UNION ALL\n                 SELECT b.parent_id, a.depth + 1 FROM blocks b\n                 INNER JOIN ancestors a ON b.id = a.id\n                 WHERE a.id IS NOT NULL AND b.is_conflict = 0 AND a.depth < 100\n             )\n             SELECT 1 as \"v: i32\" FROM ancestors WHERE id = ?",
  "describe": {
    "columns": [
      {
        "name": "v: i32",
        "ordinal": 0,
        "type_info": "Null"
      }
    ],
    "parameters": {
      "Right": 2
    },
    "nullable": [
      null
    ]
  },
  "hash": "a15a5deede38a689fb97e0776903f083a239bc4dd2aa4200013b019690fea68a"
}
