{
  "db_name": "SQLite",
  "query": "SELECT content, deleted_at, is_conflict as \"is_conflict: bool\"\n               FROM blocks WHERE id = ?",
  "describe": {
    "columns": [
      {
        "name": "content",
        "ordinal": 0,
        "type_info": "Text"
      },
      {
        "name": "deleted_at",
        "ordinal": 1,
        "type_info": "Text"
      },
      {
        "name": "is_conflict: bool",
        "ordinal": 2,
        "type_info": "Integer"
      }
    ],
    "parameters": {
      "Right": 1
    },
    "nullable": [
      true,
      true,
      false
    ]
  },
  "hash": "4c94d60168d327f2144239df0377235e30b1efbe780dcf5ed9857e45ff44c126"
}
