{
  "db_name": "SQLite",
  "query": "SELECT id, filename FROM attachments WHERE id = ?",
  "describe": {
    "columns": [
      {
        "name": "id",
        "ordinal": 0,
        "type_info": "Text",
        "origin": {
          "Table": {
            "table": "attachments",
            "name": "id"
          }
        }
      },
      {
        "name": "filename",
        "ordinal": 1,
        "type_info": "Text",
        "origin": {
          "Table": {
            "table": "attachments",
            "name": "filename"
          }
        }
      }
    ],
    "parameters": {
      "Right": 1
    },
    "nullable": [
      false,
      false
    ]
  },
  "hash": "52fcd35cc31066932d01004f78a979bbffb67b8e40eaecc07e8a75046cb379db"
}
